odoo/addons/bi_sql_editor_aggregate/README.rst
odoo/addons/bi_sql_editor_aggregate/__init__.py
odoo/addons/bi_sql_editor_aggregate/__manifest__.py
odoo/addons/bi_sql_editor_aggregate/description/icon.png
odoo/addons/bi_sql_editor_aggregate/i18n/bi_sql_editor_aggregate.pot
odoo/addons/bi_sql_editor_aggregate/models/__init__.py
odoo/addons/bi_sql_editor_aggregate/models/bi_sql_view.py
odoo/addons/bi_sql_editor_aggregate/models/bi_sql_view_field.py
odoo/addons/bi_sql_editor_aggregate/models/ir_model.py
odoo/addons/bi_sql_editor_aggregate/static/description/icon.png
odoo/addons/bi_sql_editor_aggregate/views/view_bi_sql_view.xml
odoo11_addon_bi_sql_editor_aggregate-11.0.1.0.0.99.dev5.dist-info/METADATA
odoo11_addon_bi_sql_editor_aggregate-11.0.1.0.0.99.dev5.dist-info/WHEEL
odoo11_addon_bi_sql_editor_aggregate-11.0.1.0.0.99.dev5.dist-info/top_level.txt
odoo11_addon_bi_sql_editor_aggregate-11.0.1.0.0.99.dev5.dist-info/RECORD
